{
    "title": "Docker example",
    "description": "Use docker to list all containers",
    "details": {
      "intro": {
        "text": "intro.md"
      },
      "steps": [
        {
          "title": "Create and run a container",
          "text": "step1/text.md",
          "verify": "verify.sh"
        },
        {
          "title": "Stop and remove a container",
          "text": "step2/text.md",
          "verify": "verify.sh"
        }
      ],
      "finish": {
        "text": "finish.md"
      }
    },
    "backend": {
      "imageid": "ubuntu"
    }
  }